{
  "Tiles": [
    {
      "Id": 0,
      "Name": "Empty",
      "Description": "Placed on layer 0 will create sea floor"
    },
    {
      "Id": 1,
      "Name": "Bedrock",
      "Description": "Indestructible"
    },
    {
      "Id": 2050,
      "Name": "Earth"
    },
    {
      "Id": 2051,
      "Name": "Grassy Earth"
    },
    {
      "Id": 2052,
      "Name": "Limegrassy Earth"
    },
    {
      "Id": 2053,
      "Name": "Tilled Soil"
    },
    {
      "Id": 2054,
      "Name": "Clay"
    },
    {
      "Id": 2055,
      "Name": "Mossy Earth"
    },
    {
      "Id": 2056,
      "Name": "Chalk"
    },
    {
      "Id": 2057,
      "Name": "Chunky Chalk"
    },
    {
      "Id": 2058,
      "Name": "Obsidian"
    },
    {
      "Id": 2059,
      "Name": "Sand"
    },
    {
      "Id": 2060,
      "Name": "Sandstone"
    },
    {
      "Id": 2061,
      "Name": "Sandy Sandstone"
    },
    {
      "Id": 2062,
      "Name": "Bloodstone"
    },
    {
      "Id": 2063,
      "Name": "Ash"
    },
    {
      "Id": 2064,
      "Name": "Witchgrassy Earth [*]",
      "Description": "No collision"
    },
    {
      "Id": 2065,
      "Name": "Poisonous Peat"
    },
    {
      "Id": 2066,
      "Name": "Snow Cover"
    },
    {
      "Id": 2067,
      "Name": "Snow"
    },
    {
      "Id": 2068,
      "Name": "Ice"
    },
    {
      "Id": 2069,
      "Name": "Clodstone"
    },
    {
      "Id": 2070,
      "Name": "Crumbly Clodstone"
    },
    {
      "Id": 2071,
      "Name": "Basalt"
    },
    {
      "Id": 2072,
      "Name": "Empty"
    },
    {
      "Id": 2073,
      "Name": "Lava"
    },
    {
      "Id": 2074,
      "Name": "Vault Wall"
    },
    {
      "Id": 2075,
      "Name": "Viny Vault Wall"
    },
    {
      "Id": 2076,
      "Name": "Cracked Vault Wall"
    },
    {
      "Id": 2077,
      "Name": "Mud-Brick Wall"
    },
    {
      "Id": 2078,
      "Name": "Timbered Foundation"
    },
    {
      "Id": 2079,
      "Name": "Timbered Wall Midsection"
    },
    {
      "Id": 2080,
      "Name": "Timbered Capital"
    },
    {
      "Id": 2081,
      "Name": "Hardwood Pedestal"
    },
    {
      "Id": 2082,
      "Name": "Hardwood Column Midsection"
    },
    {
      "Id": 2083,
      "Name": "Hardwood Capital"
    },
    {
      "Id": 2084,
      "Name": "Stone Foundation"
    },
    {
      "Id": 2085,
      "Name": "Stone Wall Midsection"
    },
    {
      "Id": 2086,
      "Name": "Earth [Alternate]",
      "Description": "Indestructible"
    },
    {
      "Id": 2087,
      "Name": "Castle Foundation"
    },
    {
      "Id": 2088,
      "Name": "Castle Wall Midsection"
    },
    {
      "Id": 2089,
      "Name": "Castle Crenellation"
    },
    {
      "Id": 2090,
      "Name": "Castle Battlement"
    },
    {
      "Id": 2091,
      "Name": "Wooden Wall"
    },
    {
      "Id": 2092,
      "Name": "Plumberry Lumber"
    },
    {
      "Id": 2093,
      "Name": "Flagstone"
    },
    {
      "Id": 2094,
      "Name": "Straw Floor"
    },
    {
      "Id": 2095,
      "Name": "Wooden Floor"
    },
    {
      "Id": 2096,
      "Name": "Hardwood Tile"
    },
    {
      "Id": 2097,
      "Name": "Purple Flagstone"
    },
    {
      "Id": 2098,
      "Name": "Blue Flagstone"
    },
    {
      "Id": 2099,
      "Name": "Carpet",
      "Description": "Upside down??"
    },
    {
      "Id": 2100,
      "Name": "Fancy Carpet"
    },
    {
      "Id": 2101,
      "Name": "Castle Tile"
    },
    {
      "Id": 2102,
      "Name": "Carved Castle Tile"
    },
    {
      "Id": 2103,
      "Name": "Earth [Alternate]",
      "Description": "Indestructible"
    },
    {
      "Id": 2104,
      "Name": "Earth [Alternate]",
      "Description": "Indestructible"
    },
    {
      "Id": 2105,
      "Name": "Bronze Temple Tile"
    },
    {
      "Id": 2106,
      "Name": "Blue Temple Tile"
    },
    {
      "Id": 2107,
      "Name": "Earth [Alternate]",
      "Description": "Indestructible"
    },
    {
      "Id": 2108,
      "Name": "Earth [Alternate]",
      "Description": "Indestructible"
    },
    {
      "Id": 2109,
      "Name": "Golemite [*]",
      "Description": "No collision"
    },
    {
      "Id": 2110,
      "Name": "Coal Vein"
    },
    {
      "Id": 2111,
      "Name": "Copper Vein"
    },
    {
      "Id": 2112,
      "Name": "Iron Vein"
    },
    {
      "Id": 2113,
      "Name": "Silver Vein"
    },
    {
      "Id": 2114,
      "Name": "Gold Vein"
    },
    {
      "Id": 2115,
      "Name": "Zenithium Vein"
    },
    {
      "Id": 2116,
      "Name": "Ruby Vein"
    },
    {
      "Id": 2117,
      "Name": "Mythril Vein"
    },
    {
      "Id": 2118,
      "Name": "Orichalcum Vein"
    },
    {
      "Id": 2119,
      "Name": "Earth [Alternate]",
      "Description": "Indestructible"
    },
    {
      "Id": 2120,
      "Name": "Earth [Alternate]",
      "Description": "Indestructible"
    },
    {
      "Id": 2121,
      "Name": "Golemite"
    },
    {
      "Id": 2122,
      "Name": "Palm Lumber"
    },
    {
      "Id": 2123,
      "Name": "Cedar Lumber"
    },
    {
      "Id": 2124,
      "Name": "Time-Honoured Turf"
    },
    {
      "Id": 2125,
      "Name": "8-Bit Brick"
    },
    {
      "Id": 2126,
      "Name": "Olde Worlde Wall"
    },
    {
      "Id": 2127,
      "Name": "Eyewall"
    },
    {
      "Id": 2128,
      "Name": "<<Dummy Block>>",
      "Description": "No collision"
    },
    {
      "Id": 2129,
      "Name": "Witchgrassy Earth"
    },
    {
      "Id": 2130,
      "Name": "Lemongrassy Earth"
    },
    {
      "Id": 2131,
      "Name": "<<Ore>>",
      "Description": "Drops nothing"
    },
    {
      "Id": 2132,
      "Name": "Earth [Alternate]",
      "Description": "Indestructible"
    },
    {
      "Id": 2133,
      "Name": "Strange Sand"
    },
    {
      "Id": 2134,
      "Name": "<<Red Glow>>"
    },
    {
      "Id": 2135,
      "Name": "<<Blue Glow>>"
    },
    {
      "Id": 2136,
      "Name": "Bonestone",
      "Description": "Water top?"
    },
    {
      "Id": 2137,
      "Name": "<<Evil Brick>>",
      "Description": "??"
    },
    {
      "Id": 2138,
      "Name": "Slimy Block"
    },
    {
      "Id": 2139,
      "Name": "Retro Roof"
    },
    {
      "Id": 2140,
      "Name": "Black Block"
    },
    {
      "Id": 2141,
      "Name": "Grey Block"
    },
    {
      "Id": 2142,
      "Name": "White Block"
    },
    {
      "Id": 2143,
      "Name": "Burgundy Block"
    },
    {
      "Id": 2144,
      "Name": "Red Block"
    },
    {
      "Id": 2145,
      "Name": "Purple Block"
    },
    {
      "Id": 2146,
      "Name": "Pink Block"
    },
    {
      "Id": 2147,
      "Name": "Green Block"
    },
    {
      "Id": 2148,
      "Name": "Lime-Green Block"
    },
    {
      "Id": 2149,
      "Name": "Orange Block"
    },
    {
      "Id": 2150,
      "Name": "Yellow Block"
    },
    {
      "Id": 2151,
      "Name": "Navy Block"
    },
    {
      "Id": 2152,
      "Name": "Blue Block"
    },
    {
      "Id": 2153,
      "Name": "Beige Block"
    },
    {
      "Id": 2154,
      "Name": "Cyan Block"
    },
    {
      "Id": 2155,
      "Name": "Silver Block"
    },
    {
      "Id": 2156,
      "Name": "Gold Block"
    },
    {
      "Id": 2157,
      "Name": "Fortress Foundation"
    },
    {
      "Id": 2158,
      "Name": "Fortress Wall Midsection"
    },
    {
      "Id": 2159,
      "Name": "Fortress Battlement"
    },
    {
      "Id": 2160,
      "Name": "Earth [Alternate]",
      "Description": "Indestructible"
    },
    {
      "Id": 2161,
      "Name": "Earth [Alternate]",
      "Description": "Indestructible"
    },
    {
      "Id": 2162,
      "Name": "Earth [Alternate]",
      "Description": "Indestructible"
    },
    {
      "Id": 2163,
      "Name": "Earth [Alternate|Dark]",
      "Description": "Indestructible"
    },
    {
      "Id": 2164,
      "Name": "Earth [Alternate]",
      "Description": "Indestructible"
    },
    {
      "Id": 2165,
      "Name": "Earth [Alternate]",
      "Description": "Indestructible"
    },
    {
      "Id": 2166,
      "Name": "Crumbly Clodstone [Alternate]"
    },
    {
      "Id": 2167,
      "Name": "Tilled Soil",
      "Description": "Transforms to Earth"
    },
    {
      "Id": 2168,
      "Name": "<<Liquid>>",
      "Description": "??"
    },
    {
      "Id": 2169,
      "Name": "<<Liquid>>",
      "Description": "??"
    },
    {
      "Id": 2170,
      "Name": "<<Liquid>>",
      "Description": "??"
    },
    {
      "Id": 2171,
      "Name": "<<Liquid>>",
      "Description": "??"
    },
    {
      "Id": 2172,
      "Name": "Witchgrassy Earth [Alternate]",
      "Description": "Solid Texture"
    },
    {
      "Id": 2173,
      "Name": "Lemongrassy Earth [Alternate]",
      "Description": "Solid Texture"
    },
    {
      "Id": 2174,
      "Name": "Grassy Earth [Alternate]",
      "Description": "Solid Texture"
    },
    {
      "Id": 2175,
      "Name": "Limegrassy Earth [Alternate]",
      "Description": "Solid Texture"
    },
    {
      "Id": 2176,
      "Name": "<<Liquid>>",
      "Description": "Spreads"
    },
    {
      "Id": 2177,
      "Name": "Earth [Alternate]",
      "Description": "Indestructible"
    },
    {
      "Id": 2178,
      "Name": "Light Dolomite"
    },
    {
      "Id": 2179,
      "Name": "Dark Dolomite"
    },
    {
      "Id": 2180,
      "Name": "Stony Sand"
    },
    {
      "Id": 2181,
      "Name": "Earth [Alternate]",
      "Description": "Indestructible"
    },
    {
      "Id": 2182,
      "Name": "Masonry Wall"
    },
    {
      "Id": 2183,
      "Name": "Earth [Alternate]",
      "Description": "Indestructible"
    },
    {
      "Id": 2184,
      "Name": "Earth [Alternate]",
      "Description": "Indestructible"
    },
    {
      "Id": 2185,
      "Name": "Earth [Alternate]",
      "Description": "Indestructible"
    },
    {
      "Id": 2186,
      "Name": "Mossy Bark"
    },
    {
      "Id": 2187,
      "Name": "Bark"
    },
    {
      "Id": 2188,
      "Name": "Earth [Alternate]",
      "Description": "Indestructible"
    },
    {
      "Id": 2189,
      "Name": "Stony Soil"
    },
    {
      "Id": 2190,
      "Name": "<<Liquid>>",
      "Description": "??"
    },
    {
      "Id": 2191,
      "Name": "<<Liquid>>",
      "Description": "??"
    },
    {
      "Id": 2192,
      "Name": "<<Liquid>>",
      "Description": "??"
    },
    {
      "Id": 2193,
      "Name": "<<Liquid>>",
      "Description": "??"
    },
    {
      "Id": 2194,
      "Name": "Seaside Sand"
    },
    {
      "Id": 2195,
      "Name": "Arid Earth"
    },
    {
      "Id": 2196,
      "Name": "Earth [Alternate]",
      "Description": "Indestructible"
    },
    {
      "Id": 2197,
      "Name": "Chert"
    },
    {
      "Id": 2198,
      "Name": "Earth [Alternate]",
      "Description": "Indestructible"
    },
    {
      "Id": 2199,
      "Name": "Earth [Alternate]",
      "Description": "Indestructible"
    },
    {
      "Id": 2200,
      "Name": "Earth [Alternate]",
      "Description": "Indestructible"
    },
    {
      "Id": 2201,
      "Name": "Chunky Chert"
    },
    {
      "Id": 2202,
      "Name": "Earth [Alternate]",
      "Description": "Indestructible"
    },
    {
      "Id": 2203,
      "Name": "Leaves"
    },
    {
      "Id": 2204,
      "Name": "Spoiled Soil"
    },
    {
      "Id": 2205,
      "Name": "Earth [Alternate]",
      "Description": "Indestructible"
    },
    {
      "Id": 2206,
      "Name": "Moss"
    },
    {
      "Id": 2207,
      "Name": "Earth [Alternate]",
      "Description": "Indestructible"
    },
    {
      "Id": 2208,
      "Name": "Earth [Alternate]",
      "Description": "Indestructible"
    },
    {
      "Id": 2209,
      "Name": "Humus"
    },
    {
      "Id": 2210,
      "Name": "Tilled Humus"
    },
    {
      "Id": 2211,
      "Name": "Obsidian [Alternate]",
      "Description": "Indestructible"
    },
    {
      "Id": 2212,
      "Name": "Blue Temple Tile",
      "Description": "Indestructible"
    },
    {
      "Id": 2213,
      "Name": "??",
      "Description": "Indestructible"
    },
    {
      "Id": 2214,
      "Name": "??",
      "Description": "Indestructible"
    },
    {
      "Id": 2215,
      "Name": "??",
      "Description": "Indestructible"
    },
    {
      "Id": 2216,
      "Name": "??",
      "Description": "Indestructible"
    },
    {
      "Id": 2217,
      "Name": "??",
      "Description": "Indestructible"
    },
    {
      "Id": 2218,
      "Name": "??",
      "Description": "Indestructible"
    },
    {
      "Id": 2219,
      "Name": "??",
      "Description": "Indestructible"
    },
    {
      "Id": 2220,
      "Name": "Tilled Soil",
      "Description": "??"
    },
    {
      "Id": 2221,
      "Name": "Tilled Humus"
    },
    {
      "Id": 2222,
      "Name": "Chert",
      "Description": "??"
    },
    {
      "Id": 2223,
      "Name": "Bubbling Seaside Sand"
    },
    {
      "Id": 2224,
      "Name": "??",
      "Description": "Indestructible"
    },
    {
      "Id": 2225,
      "Name": "??",
      "Description": "Indestructible"
    },
    {
      "Id": 2226,
      "Name": "??",
      "Description": "Indestructible"
    },
    {
      "Id": 2227,
      "Name": "??",
      "Description": "Indestructible"
    },
    {
      "Id": 2228,
      "Name": "??",
      "Description": "Indestructible"
    },
    {
      "Id": 2229,
      "Name": "??",
      "Description": "Indestructible"
    },
    {
      "Id": 2230,
      "Name": "Earth [Alternate]",
      "Description": "Indestructible"
    },
    {
      "Id": 2231,
      "Name": "<<Liquid>>",
      "Description": "??"
    },
    {
      "Id": 2232,
      "Name": "<<Liquid>>",
      "Description": "??"
    },
    {
      "Id": 2233,
      "Name": "<<Liquid>>",
      "Description": "??"
    },
    {
      "Id": 2234,
      "Name": "<<Liquid>>",
      "Description": "??"
    },
    {
      "Id": 2235,
      "Name": "<<Liquid>>",
      "Description": "??"
    },
    {
      "Id": 2236,
      "Name": "<<Liquid>>",
      "Description": "??"
    },
    {
      "Id": 2237,
      "Name": "<<Liquid>>",
      "Description": "??"
    },
    {
      "Id": 2238,
      "Name": "<<Liquid>>",
      "Description": "??"
    },
    {
      "Id": 2239,
      "Name": "<<Liquid>>",
      "Description": "??"
    },
    {
      "Id": 2240,
      "Name": "<<Liquid>>",
      "Description": "??"
    },
    {
      "Id": 2241,
      "Name": "<<Liquid>>",
      "Description": "??"
    },
    {
      "Id": 2242,
      "Name": "<<Liquid>>",
      "Description": "??"
    },
    {
      "Id": 2243,
      "Name": "<<Liquid>>",
      "Description": "??"
    },
    {
      "Id": 2244,
      "Name": "<<Liquid>>",
      "Description": "??"
    },
    {
      "Id": 2245,
      "Name": "<<Liquid>>",
      "Description": "??"
    },
    {
      "Id": 2246,
      "Name": "<<Liquid>>",
      "Description": "??"
    },
    {
      "Id": 2247,
      "Name": "<<Liquid>>",
      "Description": "??"
    },
    {
      "Id": 2248,
      "Name": "<<Liquid>>",
      "Description": "??"
    },
    {
      "Id": 2249,
      "Name": "<<Liquid>>",
      "Description": "??"
    },
    {
      "Id": 2250,
      "Name": "<<Liquid>>",
      "Description": "??"
    },
    {
      "Id": 2251,
      "Name": "<<Liquid>>",
      "Description": "??"
    },
    {
      "Id": 2252,
      "Name": "<<Liquid>>",
      "Description": "??"
    },
    {
      "Id": 2253,
      "Name": "<<Liquid>>",
      "Description": "??"
    },
    {
      "Id": 2254,
      "Name": "<<Liquid>>",
      "Description": "??"
    },
    {
      "Id": 2255,
      "Name": "<<Liquid>>",
      "Description": "??"
    },
    {
      "Id": 2256,
      "Name": "<<Liquid>>",
      "Description": "??"
    },
    {
      "Id": 2257,
      "Name": "<<Liquid>>",
      "Description": "??"
    },
    {
      "Id": 2258,
      "Name": "Umber"
    },
    {
      "Id": 2259,
      "Name": "??",
      "Description": "??"
    },
    {
      "Id": 2260,
      "Name": "Earth [Alternate]",
      "Description": "Indestructible"
    },
    {
      "Id": 2261,
      "Name": "Earth [Alternate]",
      "Description": "Indestructible"
    },
    {
      "Id": 2262,
      "Name": "Earth [Alternate]",
      "Description": "Indestructible"
    },
    {
      "Id": 2263,
      "Name": "Earth [Alternate]",
      "Description": "Indestructible"
    },
    {
      "Id": 2264,
      "Name": "Earth [Alternate]",
      "Description": "Indestructible"
    },
    {
      "Id": 2265,
      "Name": "Earth [Alternate]",
      "Description": "Indestructible"
    },
    {
      "Id": 2266,
      "Name": "Earth [Alternate]",
      "Description": "Indestructible"
    },
    {
      "Id": 2267,
      "Name": "Earth [Alternate]",
      "Description": "Indestructible"
    },
    {
      "Id": 2268,
      "Name": "Earth [Alternate]",
      "Description": "Indestructible"
    },
    {
      "Id": 2269,
      "Name": "Earth [Alternate]",
      "Description": "Indestructible"
    },
    {
      "Id": 2270,
      "Name": "Earth [Alternate]",
      "Description": "Indestructible"
    },
    {
      "Id": 2271,
      "Name": "<<Liquid>>",
      "Description": "??"
    },
    {
      "Id": 2272,
      "Name": "<<Liquid>>",
      "Description": "??"
    },
    {
      "Id": 2273,
      "Name": "<<Liquid>>",
      "Description": "??"
    },
    {
      "Id": 2274,
      "Name": "<<Liquid>>",
      "Description": "??"
    },
    {
      "Id": 2275,
      "Name": "<<Liquid>>",
      "Description": "??"
    },
    {
      "Id": 2276,
      "Name": "<<Liquid>>",
      "Description": "??"
    },
    {
      "Id": 2277,
      "Name": "<<Liquid>>",
      "Description": "??"
    },
    {
      "Id": 2278,
      "Name": "<<Liquid>>",
      "Description": "??"
    },
    {
      "Id": 2279,
      "Name": "<<Liquid>>",
      "Description": "??"
    },
    {
      "Id": 2280,
      "Name": "<<Liquid>>",
      "Description": "??"
    },
    {
      "Id": 2281,
      "Name": "Mossy Spoiled Soil"
    },
    {
      "Id": 2282,
      "Name": "??",
      "Description": "??"
    },
    {
      "Id": 2283,
      "Name": "Swampy Soil"
    },
    {
      "Id": 2284,
      "Name": "Seeded Spoiled Soil",
      "Description": "Drops Grass Seed"
    },
    {
      "Id": 2285,
      "Name": "Seeded Spoiled Soil",
      "Description": "Drops Tomato Seed"
    },
    {
      "Id": 2286,
      "Name": "Earth [Alternate]",
      "Description": "Indestructible"
    },
    {
      "Id": 2287,
      "Name": "Earth [Alternate]",
      "Description": "Indestructible"
    },
    {
      "Id": 2288,
      "Name": "Seeded Spoiled Soil",
      "Description": "Drops Sugar Cane Seedling"
    },
    {
      "Id": 2289,
      "Name": "Earth [Alternate]",
      "Description": "Indestructible"
    },
    {
      "Id": 2290,
      "Name": "Lumpy Umber"
    },
    {
      "Id": 2291,
      "Name": "Earth [Alternate]",
      "Description": "Indestructible"
    },
    {
      "Id": 2292,
      "Name": "Softwood"
    },
    {
      "Id": 2293,
      "Name": "Floorboard"
    },
    {
      "Id": 2294,
      "Name": "Earth [Alternate]",
      "Description": "Indestructible"
    },
    {
      "Id": 2295,
      "Name": "Earth [Alternate]",
      "Description": "Indestructible"
    },
    {
      "Id": 2296,
      "Name": "<<Outline Block>>",
      "Description": "Seethrough"
    },
    {
      "Id": 2297,
      "Name": "Earth [Alternate]",
      "Description": "Indestructible"
    },
    {
      "Id": 2298,
      "Name": "Earth [Alternate]",
      "Description": "Indestructible"
    },
    {
      "Id": 2299,
      "Name": "Earth [Alternate]",
      "Description": "Indestructible"
    },
    {
      "Id": 2300,
      "Name": "Earth [Alternate]",
      "Description": "Indestructible"
    },
    {
      "Id": 2301,
      "Name": "Earth [Alternate]",
      "Description": "Indestructible"
    },
    {
      "Id": 2302,
      "Name": "Earth [Alternate]",
      "Description": "Indestructible"
    },
    {
      "Id": 2303,
      "Name": "Earth [Alternate]",
      "Description": "Indestructible"
    },
    {
      "Id": 2304,
      "Name": "Mossy Spoiled Soil [Alternate]"
    },
    {
      "Id": 2305,
      "Name": "Earth [Alternate]",
      "Description": "Indestructible"
    },
    {
      "Id": 2306,
      "Name": "Earth [Alternate]",
      "Description": "Indestructible"
    },
    {
      "Id": 2307,
      "Name": "<<Liquid>>",
      "Description": "??"
    },
    {
      "Id": 2308,
      "Name": "<<Liquid>>",
      "Description": "??"
    },
    {
      "Id": 2309,
      "Name": "<<Liquid>>",
      "Description": "??"
    },
    {
      "Id": 2310,
      "Name": "<<Liquid>>",
      "Description": "??"
    },
    {
      "Id": 2311,
      "Name": "<<Liquid>>",
      "Description": "??"
    },
    {
      "Id": 2312,
      "Name": "<<Liquid>>",
      "Description": "??"
    },
    {
      "Id": 2313,
      "Name": "<<Liquid>>",
      "Description": "??"
    },
    {
      "Id": 2314,
      "Name": "<<Liquid>>",
      "Description": "??"
    },
    {
      "Id": 2315,
      "Name": "<<Liquid>>",
      "Description": "??"
    },
    {
      "Id": 2316,
      "Name": "Patterned Vault Wall"
    },
    {
      "Id": 2317,
      "Name": "Fancy Carpet [White]"
    },
    {
      "Id": 2318,
      "Name": "Fancy Carpet [Black]"
    },
    {
      "Id": 2319,
      "Name": "Fancy Carpet [Purple]"
    },
    {
      "Id": 2320,
      "Name": "Fancy Carpet [Pink]"
    },
    {
      "Id": 2321,
      "Name": "Fancy Carpet [Green]"
    },
    {
      "Id": 2322,
      "Name": "Fancy Carpet [Yellow]"
    },
    {
      "Id": 2323,
      "Name": "Fancy Carpet [Blue]"
    },
    {
      "Id": 2324,
      "Name": "Fancy Carpet [Red]"
    },
    {
      "Id": 2325,
      "Name": "Timbered Foundation [White]"
    },
    {
      "Id": 2326,
      "Name": "Timbered Foundation [Black]"
    },
    {
      "Id": 2327,
      "Name": "Timbered Foundation [Purple]"
    },
    {
      "Id": 2328,
      "Name": "Timbered Foundation [Pink]"
    },
    {
      "Id": 2329,
      "Name": "Timbered Foundation [Red]"
    },
    {
      "Id": 2330,
      "Name": "Timbered Foundation [Green]"
    },
    {
      "Id": 2331,
      "Name": "Timbered Foundation [Yellow]"
    },
    {
      "Id": 2332,
      "Name": "Timbered Foundation [Blue]"
    },
    {
      "Id": 2333,
      "Name": "Timbered Wall Midsection [White]"
    },
    {
      "Id": 2334,
      "Name": "Timbered Wall Midsection [Black]"
    },
    {
      "Id": 2335,
      "Name": "Timbered Wall Midsection [Purple]"
    },
    {
      "Id": 2336,
      "Name": "Timbered Wall Midsection [Pink]"
    },
    {
      "Id": 2337,
      "Name": "Timbered Wall Midsection [Red]"
    },
    {
      "Id": 2338,
      "Name": "Timbered Wall Midsection [Green]"
    },
    {
      "Id": 2339,
      "Name": "Timbered Wall Midsection [Yellow]"
    },
    {
      "Id": 2340,
      "Name": "Timbered Wall Midsection [Blue]"
    },
    {
      "Id": 2341,
      "Name": "Timbered Capital [White]"
    },
    {
      "Id": 2342,
      "Name": "Timbered Capital [Black]"
    },
    {
      "Id": 2343,
      "Name": "Timbered Capital [Purple]"
    },
    {
      "Id": 2344,
      "Name": "Timbered Capital [Pink]"
    },
    {
      "Id": 2345,
      "Name": "Timbered Capital [Red]"
    },
    {
      "Id": 2346,
      "Name": "Timbered Capital [Green]"
    },
    {
      "Id": 2347,
      "Name": "Timbered Capital [Yellow]"
    },
    {
      "Id": 2348,
      "Name": "Timbered Capital [Blue]"
    },
    {
      "Id": 2349,
      "Name": "Wooden Wall [White]"
    },
    {
      "Id": 2350,
      "Name": "Wooden Wall [Black]"
    },
    {
      "Id": 2351,
      "Name": "Wooden Wall [Purple]"
    },
    {
      "Id": 2352,
      "Name": "Wooden Wall [Pink]"
    },
    {
      "Id": 2353,
      "Name": "Wooden Wall [Red]"
    },
    {
      "Id": 2354,
      "Name": "Wooden Wall [Green]"
    },
    {
      "Id": 2355,
      "Name": "Wooden Wall [Yellow]"
    },
    {
      "Id": 2356,
      "Name": "Wooden Wall [Blue]"
    },
    {
      "Id": 2357,
      "Name": "Carpet [White]"
    },
    {
      "Id": 2358,
      "Name": "Carpet [Black]"
    },
    {
      "Id": 2359,
      "Name": "Carpet [Purple]"
    },
    {
      "Id": 2360,
      "Name": "Carpet [Pink]"
    },
    {
      "Id": 2361,
      "Name": "Carpet [Red]"
    },
    {
      "Id": 2362,
      "Name": "Carpet [Green]"
    },
    {
      "Id": 2363,
      "Name": "Carpet [Yellow]"
    },
    {
      "Id": 2364,
      "Name": "Carpet [Blue]"
    },
    {
      "Id": 2365,
      "Name": "Wooden Floor [White]"
    },
    {
      "Id": 2366,
      "Name": "Wooden Floor [Black]"
    },
    {
      "Id": 2367,
      "Name": "Wooden Floor [Purple]"
    },
    {
      "Id": 2368,
      "Name": "Wooden Floor [Pink]"
    },
    {
      "Id": 2369,
      "Name": "Wooden Floor [Red]"
    },
    {
      "Id": 2370,
      "Name": "Wooden Floor [Green]"
    },
    {
      "Id": 2371,
      "Name": "Wooden Floor [Yellow]"
    },
    {
      "Id": 2372,
      "Name": "Wooden Floor [Blue]"
    },
    {
      "Id": 2373,
      "Name": "Earth [Alternate]",
      "Description": "Indestructible"
    },
    {
      "Id": 2374,
      "Name": "Earth [Alternate]",
      "Description": "Indestructible"
    },
    {
      "Id": 2375,
      "Name": "Earth [Alternate]",
      "Description": "Indestructible"
    },
    {
      "Id": 2376,
      "Name": "Earth [Alternate]",
      "Description": "Indestructible"
    },
    {
      "Id": 2377,
      "Name": "Earth [Alternate]",
      "Description": "Indestructible"
    },
    {
      "Id": 2378,
      "Name": "Earth [Alternate]",
      "Description": "Indestructible"
    },
    {
      "Id": 2379,
      "Name": "Shifting Sand"
    },
    {
      "Id": 2380,
      "Name": "Earth [Alternate]",
      "Description": "Indestructible"
    },
    {
      "Id": 2381,
      "Name": "<<Liquid>>",
      "Description": "??"
    },
    {
      "Id": 2382,
      "Name": "<<Liquid>>",
      "Description": "??"
    },
    {
      "Id": 2383,
      "Name": "<<Liquid>>",
      "Description": "??"
    },
    {
      "Id": 2384,
      "Name": "<<Liquid>>",
      "Description": "??"
    },
    {
      "Id": 2385,
      "Name": "<<Liquid>>",
      "Description": "??"
    },
    {
      "Id": 2386,
      "Name": "<<Liquid>>",
      "Description": "??"
    },
    {
      "Id": 2387,
      "Name": "<<Liquid>>",
      "Description": "??"
    },
    {
      "Id": 2388,
      "Name": "<<Liquid>>",
      "Description": "??"
    },
    {
      "Id": 2389,
      "Name": "<<Liquid>>",
      "Description": "??"
    },
    {
      "Id": 2390,
      "Name": "Earth [Alternate]",
      "Description": "Indestructible"
    },
    {
      "Id": 2391,
      "Name": "<<Liquid>>",
      "Description": "??"
    },
    {
      "Id": 2392,
      "Name": "<<Liquid>>",
      "Description": "??"
    },
    {
      "Id": 2393,
      "Name": "<<Liquid>>",
      "Description": "??"
    },
    {
      "Id": 2394,
      "Name": "<<Liquid>>",
      "Description": "??"
    },
    {
      "Id": 2395,
      "Name": "<<Liquid>>",
      "Description": "??"
    },
    {
      "Id": 2396,
      "Name": "<<Liquid>>",
      "Description": "??"
    },
    {
      "Id": 2397,
      "Name": "<<Liquid>>",
      "Description": "??"
    },
    {
      "Id": 2398,
      "Name": "Earth [Alternate]",
      "Description": "Indestructible"
    },
    {
      "Id": 2399,
      "Name": "Hardwood Column Midsection [White]"
    },
    {
      "Id": 2400,
      "Name": "Hardwood Column Midsection [Black]"
    },
    {
      "Id": 2401,
      "Name": "Hardwood Column Midsection [Purple]"
    },
    {
      "Id": 2402,
      "Name": "Hardwood Column Midsection [Pink]"
    },
    {
      "Id": 2403,
      "Name": "Hardwood Column Midsection [Red]"
    },
    {
      "Id": 2404,
      "Name": "Hardwood Column Midsection [Green]"
    },
    {
      "Id": 2405,
      "Name": "Hardwood Column Midsection [Yellow]"
    },
    {
      "Id": 2406,
      "Name": "Hardwood Column Midsection [Blue]"
    },
    {
      "Id": 2407,
      "Name": "Hardwood Pedestal [White]"
    },
    {
      "Id": 2408,
      "Name": "Hardwood Pedestal [Black]"
    },
    {
      "Id": 2409,
      "Name": "Hardwood Pedestal [Purple]"
    },
    {
      "Id": 2410,
      "Name": "Hardwood Pedestal [Pink]"
    },
    {
      "Id": 2411,
      "Name": "Hardwood Pedestal [Red]"
    },
    {
      "Id": 2412,
      "Name": "Hardwood Pedestal [Green]"
    },
    {
      "Id": 2413,
      "Name": "Hardwood Pedestal [Yellow]"
    },
    {
      "Id": 2414,
      "Name": "Hardwood Pedestal [Blue]"
    },
    {
      "Id": 2415,
      "Name": "Hardwood Capital [White]"
    },
    {
      "Id": 2416,
      "Name": "Hardwood Capital [Black]"
    },
    {
      "Id": 2417,
      "Name": "Hardwood Capital [Purple]"
    },
    {
      "Id": 2418,
      "Name": "Hardwood Capital [Pink]"
    },
    {
      "Id": 2419,
      "Name": "Hardwood Capital [Red]"
    },
    {
      "Id": 2420,
      "Name": "Hardwood Capital [Green]"
    },
    {
      "Id": 2421,
      "Name": "Hardwood Capital [Yellow]"
    },
    {
      "Id": 2422,
      "Name": "Hardwood Capital [Blue]"
    },
    {
      "Id": 2423,
      "Name": "Carpet [White]",
      "Description": "Upside down"
    },
    {
      "Id": 2424,
      "Name": "Carpet [Black]",
      "Description": "Upside down"
    },
    {
      "Id": 2425,
      "Name": "Carpet [Purple]",
      "Description": "Upside down"
    },
    {
      "Id": 2426,
      "Name": "Carpet [Pink]",
      "Description": "Upside down"
    },
    {
      "Id": 2427,
      "Name": "Carpet [Red]",
      "Description": "Upside down"
    },
    {
      "Id": 2428,
      "Name": "Carpet [Green]",
      "Description": "Upside down"
    },
    {
      "Id": 2429,
      "Name": "Carpet [Yellow]",
      "Description": "Upside down"
    },
    {
      "Id": 2430,
      "Name": "Carpet [Blue]",
      "Description": "Upside down"
    },
    {
      "Id": 2431,
      "Name": "<<Liquid>>",
      "Description": "??"
    },
    {
      "Id": 2432,
      "Name": "<<Liquid>>",
      "Description": "??"
    },
    {
      "Id": 2433,
      "Name": "<<Liquid>>",
      "Description": "??"
    },
    {
      "Id": 2434,
      "Name": "<<Liquid>>",
      "Description": "??"
    },
    {
      "Id": 2435,
      "Name": "<<Liquid>>",
      "Description": "??"
    },
    {
      "Id": 2436,
      "Name": "<<Liquid>>",
      "Description": "??"
    },
    {
      "Id": 2437,
      "Name": "<<Liquid>>",
      "Description": "??"
    },
    {
      "Id": 2438,
      "Name": "<<Liquid>>",
      "Description": "??"
    },
    {
      "Id": 2439,
      "Name": "<<Liquid>>",
      "Description": "??"
    },
    {
      "Id": 2440,
      "Name": "<<Liquid>>",
      "Description": "??"
    },
    {
      "Id": 2441,
      "Name": "<<Liquid>>",
      "Description": "??"
    },
    {
      "Id": 2442,
      "Name": "<<Liquid>>",
      "Description": "??"
    },
    {
      "Id": 2443,
      "Name": "<<Liquid>>",
      "Description": "??"
    },
    {
      "Id": 2444,
      "Name": "<<Liquid>>",
      "Description": "??"
    },
    {
      "Id": 2445,
      "Name": "<<Liquid>>",
      "Description": "??"
    },
    {
      "Id": 2446,
      "Name": "<<Liquid>>",
      "Description": "??"
    },
    {
      "Id": 2447,
      "Name": "<<Liquid>>",
      "Description": "??"
    },
    {
      "Id": 2448,
      "Name": "<<Liquid>>",
      "Description": "??"
    },
    {
      "Id": 2449,
      "Name": "Vault Tile"
    },
    {
      "Id": 2450,
      "Name": "Gold Brick"
    },
    {
      "Id": 2451,
      "Name": "Spaceship Wall"
    },
    {
      "Id": 2452,
      "Name": "Shiny Spaceship Wall"
    },
    {
      "Id": 2453,
      "Name": "Citadel Battlement"
    },
    {
      "Id": 2454,
      "Name": "Earth [Alternate]",
      "Description": "Indestructible"
    },
    {
      "Id": 2455,
      "Name": "Golden Citadel Capital"
    },
    {
      "Id": 2456,
      "Name": "Alcoved Citadel Wall"
    },
    {
      "Id": 2457,
      "Name": "Golden Citadel Foundation"
    },
    {
      "Id": 2458,
      "Name": "Patterned Citadel Wall"
    },
    {
      "Id": 2459,
      "Name": "Golden Tile"
    },
    {
      "Id": 2460,
      "Name": "<<Evil Brick>>",
      "Description": "??"
    },
    {
      "Id": 2461,
      "Name": "<<Black Block>>",
      "Description": "No collision, Indestructible"
    },
    {
      "Id": 2462,
      "Name": "Earth [Alternate]",
      "Description": "Indestructible"
    },
    {
      "Id": 2463,
      "Name": "Mossy Earth [Alternate]",
      "Description": "Indestructible"
    },
    {
      "Id": 2464,
      "Name": "??",
      "Description": "Indestructible"
    },
    {
      "Id": 2465,
      "Name": "??",
      "Description": "Indestructible"
    },
    {
      "Id": 2466,
      "Name": "??",
      "Description": "Indestructible"
    },
    {
      "Id": 2467,
      "Name": "??",
      "Description": "Indestructible"
    },
    {
      "Id": 2468,
      "Name": "<<Liquid>>",
      "Description": "??"
    },
    {
      "Id": 2469,
      "Name": "Spaceship Wall [White]"
    },
    {
      "Id": 2470,
      "Name": "Spaceship Wall [Black]"
    },
    {
      "Id": 2471,
      "Name": "Spaceship Wall [Purple]"
    },
    {
      "Id": 2472,
      "Name": "Spaceship Wall [Pink]"
    },
    {
      "Id": 2473,
      "Name": "Spaceship Wall [Red]"
    },
    {
      "Id": 2474,
      "Name": "Spaceship Wall [Green]"
    },
    {
      "Id": 2475,
      "Name": "Spaceship Wall [Yellow]"
    },
    {
      "Id": 2476,
      "Name": "Spaceship Wall [Blue]"
    },
    {
      "Id": 2477,
      "Name": "Shiny Spaceship Wall [White]"
    },
    {
      "Id": 2478,
      "Name": "Shiny Spaceship Wall [Black]"
    },
    {
      "Id": 2479,
      "Name": "Shiny Spaceship Wall [Purple]"
    },
    {
      "Id": 2480,
      "Name": "Shiny Spaceship Wall [Pink]"
    },
    {
      "Id": 2481,
      "Name": "Shiny Spaceship Wall [Red]"
    },
    {
      "Id": 2482,
      "Name": "Shiny Spaceship Wall [Green]"
    },
    {
      "Id": 2483,
      "Name": "Shiny Spaceship Wall [Yellow]"
    },
    {
      "Id": 2484,
      "Name": "Shiny Spaceship Wall [Blue]"
    },
    {
      "Id": 2485,
      "Name": "Woodless Timbered Wall"
    },
    {
      "Id": 2486,
      "Name": "Banded Timbered Wall"
    },
    {
      "Id": 2487,
      "Name": "<<Snow Block>>"
    },
    {
      "Id": 2488,
      "Name": "<<Snow Block>>"
    },
    {
      "Id": 2489,
      "Name": "<<Snow Block>>"
    },
    {
      "Id": 2490,
      "Name": "<<Snow Block>>"
    },
    {
      "Id": 2491,
      "Name": "<<Snow Block>>"
    },
    {
      "Id": 2492,
      "Name": "<<Snow Block>>"
    },
    {
      "Id": 2493,
      "Name": "<<Snow Block>>"
    },
    {
      "Id": 2494,
      "Name": "<<Snow Block>>"
    },
    {
      "Id": 2495,
      "Name": "Banded Timbered Wall [White]"
    },
    {
      "Id": 2496,
      "Name": "Banded Timbered Wall [Black]"
    },
    {
      "Id": 2497,
      "Name": "Banded Timbered Wall [Purple]"
    },
    {
      "Id": 2498,
      "Name": "Banded Timbered Wall [Pink]"
    },
    {
      "Id": 2499,
      "Name": "Banded Timbered Wall [Red]"
    },
    {
      "Id": 2500,
      "Name": "Banded Timbered Wall [Green]"
    },
    {
      "Id": 2501,
      "Name": "Banded Timbered Wall [Yellow]"
    },
    {
      "Id": 2502,
      "Name": "Banded Timbered Wall [Blue]"
    },
    {
      "Id": 2503,
      "Name": "Earth [Alternate]",
      "Description": "Indestructible"
    },
    {
      "Id": 2504,
      "Name": "Earth [Alternate]",
      "Description": "Indestructible"
    },
    {
      "Id": 2505,
      "Name": "Earth [Alternate]",
      "Description": "Indestructible"
    },
    {
      "Id": 2506,
      "Name": "Earth [Alternate]",
      "Description": "Indestructible"
    },
    {
      "Id": 2507,
      "Name": "Earth [Alternate]",
      "Description": "Indestructible"
    },
    {
      "Id": 2508,
      "Name": "Earth [Alternate]",
      "Description": "Indestructible"
    },
    {
      "Id": 2509,
      "Name": "Earth [Alternate]",
      "Description": "Indestructible"
    },
    {
      "Id": 2510,
      "Name": "Earth [Alternate]",
      "Description": "Indestructible"
    },
    {
      "Id": 2511,
      "Name": "Hardwood Tile [White]"
    },
    {
      "Id": 2512,
      "Name": "Hardwood Tile [Black]"
    },
    {
      "Id": 2513,
      "Name": "Hardwood Tile [Purple]"
    },
    {
      "Id": 2514,
      "Name": "Hardwood Tile [Pink]"
    },
    {
      "Id": 2515,
      "Name": "Hardwood Tile [Red]"
    },
    {
      "Id": 2516,
      "Name": "Hardwood Tile [Green]"
    },
    {
      "Id": 2517,
      "Name": "Hardwood Tile [Yellow]"
    },
    {
      "Id": 2518,
      "Name": "Hardwood Tile [Blue]"
    },
    {
      "Id": 2519,
      "Name": "Earth [Alternate]",
      "Description": "Indestructible"
    },
    {
      "Id": 2520,
      "Name": "Red-Brick Wall"
    },
    {
      "Id": 2521,
      "Name": "Diamon Vein"
    },
    {
      "Id": 2522,
      "Name": "??"
    },
    {
      "Id": 2523,
      "Name": "??"
    },
    {
      "Id": 2524,
      "Name": "Magnetite Vein"
    },
    {
      "Id": 2525,
      "Name": "Siltstone"
    },
    {
      "Id": 2526,
      "Name": "Earth [Alternate]",
      "Description": "Indestructible"
    },
    {
      "Id": 2527,
      "Name": "Earth [Alternate]",
      "Description": "Indestructible"
    },
    {
      "Id": 2528,
      "Name": "Earth [Alternate]",
      "Description": "Indestructible"
    },
    {
      "Id": 2529,
      "Name": "??"
    },
    {
      "Id": 2530,
      "Name": "Earth [Alternate]",
      "Description": "Indestructible"
    },
    {
      "Id": 2531,
      "Name": "Earth [Alternate]",
      "Description": "Indestructible"
    },
    {
      "Id": 2532,
      "Name": "Red-Brick Floor"
    },
    {
      "Id": 2533,
      "Name": "Crazing Paving"
    },
    {
      "Id": 2534,
      "Name": "Copper Wall"
    },
    {
      "Id": 2535,
      "Name": "Marble"
    },
    {
      "Id": 2536,
      "Name": "Silver Birch Lumber"
    },
    {
      "Id": 2537,
      "Name": "Earth [Alternate]",
      "Description": "Indestructible"
    },
    {
      "Id": 2538,
      "Name": "Dark Bark"
    },
    {
      "Id": 2539,
      "Name": "Teal Leaves"
    },
    {
      "Id": 2540,
      "Name": "Earth [Alternate]",
      "Description": "Indestructible"
    },
    {
      "Id": 2541,
      "Name": "Earth [Alternate]",
      "Description": "Indestructible"
    },
    {
      "Id": 2542,
      "Name": "Earth [Alternate]",
      "Description": "Indestructible"
    },
    {
      "Id": 2543,
      "Name": "Earth [Alternate]",
      "Description": "Indestructible"
    },
    {
      "Id": 2544,
      "Name": "Bloodstained Soil"
    },
    {
      "Id": 2545,
      "Name": "Bloodstained Soil [Alternate]"
    },
    {
      "Id": 2546,
      "Name": "Padded Floor"
    },
    {
      "Id": 2547,
      "Name": "Leafy Spoiled Soil"
    },
    {
      "Id": 2548,
      "Name": "Leafy Spoiled Soil [Alternate]"
    },
    {
      "Id": 2549,
      "Name": "Earth [Alternate]",
      "Description": "Indestructible"
    },
    {
      "Id": 2550,
      "Name": "Earth [Alternate]",
      "Description": "Indestructible"
    },
    {
      "Id": 2551,
      "Name": "Earth [Alternate]",
      "Description": "Indestructible"
    },
    {
      "Id": 2552,
      "Name": "Earth [Alternate]",
      "Description": "Indestructible"
    },
    {
      "Id": 2553,
      "Name": "Earth [Alternate]",
      "Description": "Indestructible"
    },
    {
      "Id": 2554,
      "Name": "Earth [Alternate]",
      "Description": "Indestructible"
    },
    {
      "Id": 2555,
      "Name": "Earth [Alternate]",
      "Description": "Indestructible"
    },
    {
      "Id": 2556,
      "Name": "Earth [Alternate]",
      "Description": "Indestructible"
    },
    {
      "Id": 2557,
      "Name": "Earth [Alternate]",
      "Description": "Indestructible"
    },
    {
      "Id": 2558,
      "Name": "Earth [Alternate]",
      "Description": "Indestructible"
    },
    {
      "Id": 2559,
      "Name": "Earth [Alternate]",
      "Description": "Indestructible"
    },
    {
      "Id": 2560,
      "Name": "Earth [Alternate]",
      "Description": "Indestructible"
    },
    {
      "Id": 2561,
      "Name": "Earth [Alternate]",
      "Description": "Indestructible"
    },
    {
      "Id": 2562,
      "Name": "Earth [Alternate]",
      "Description": "Indestructible"
    },
    {
      "Id": 2563,
      "Name": "Earth [Alternate]",
      "Description": "Indestructible"
    },
    {
      "Id": 2564,
      "Name": "Earth [Alternate]",
      "Description": "Indestructible"
    },
    {
      "Id": 2565,
      "Name": "Earth [Alternate]",
      "Description": "Indestructible"
    },
    {
      "Id": 2566,
      "Name": "Earth [Alternate]",
      "Description": "Indestructible"
    },
    {
      "Id": 2567,
      "Name": "Cracked Floorboard"
    },
    {
      "Id": 2568,
      "Name": "Blackened Bark"
    },
    {
      "Id": 2569,
      "Name": "Bloodstained Soil [Alternate]"
    },
    {
      "Id": 2570,
      "Name": "Malachite"
    },
    {
      "Id": 2571,
      "Name": "Patterned Vault Wall"
    },
    {
      "Id": 2572,
      "Name": "Patterned Vault Wall [Alternate]"
    },
    {
      "Id": 2573,
      "Name": "Adobe Capital"
    },
    {
      "Id": 2574,
      "Name": "Adobe Wall"
    },
    {
      "Id": 2575,
      "Name": "Adobe Pedestal"
    },
    {
      "Id": 2576,
      "Name": "Alcoved Adobe Wall"
    },
    {
      "Id": 2577,
      "Name": "Copper Floor"
    },
    {
      "Id": 2578,
      "Name": "Sooty Softwood"
    },
    {
      "Id": 2579,
      "Name": "Earth [Alternate]",
      "Description": "Indestructible"
    },
    {
      "Id": 2580,
      "Name": "Heartwood"
    },
    {
      "Id": 2581,
      "Name": "??"
    },
    {
      "Id": 2582,
      "Name": "White Dye Vein"
    },
    {
      "Id": 2583,
      "Name": "Black Dye Vein"
    },
    {
      "Id": 2584,
      "Name": "Purple Dye Vein"
    },
    {
      "Id": 2585,
      "Name": "Pink Dye Vein"
    },
    {
      "Id": 2586,
      "Name": "Red Dye Vein"
    },
    {
      "Id": 2587,
      "Name": "Green Dye Vein"
    },
    {
      "Id": 2588,
      "Name": "Yellow Dye Vein"
    },
    {
      "Id": 2589,
      "Name": "Blue Dye Vein"
    },
    {
      "Id": 2590,
      "Name": "Earth [Alternate]",
      "Description": "Indestructible"
    },
    {
      "Id": 2591,
      "Name": "Blue Temple Tile",
      "Description": "Indestructible"
    },
    {
      "Id": 2592,
      "Name": "Carpet",
      "Description": "??"
    },
    {
      "Id": 2593,
      "Name": "Golden Castle Capital"
    },
    {
      "Id": 2594,
      "Name": "Alcoved Castle Wall"
    },
    {
      "Id": 2595,
      "Name": "Golden Castle Foundation"
    },
    {
      "Id": 2596,
      "Name": "Cracked Castle Tile"
    },
    {
      "Id": 2597,
      "Name": "Battlefield Earth"
    },
    {
      "Id": 2598,
      "Name": "Citadel Capital"
    },
    {
      "Id": 2599,
      "Name": "Citadel Foundation"
    },
    {
      "Id": 2600,
      "Name": "Citadel Wall Midsection"
    },
    {
      "Id": 2601,
      "Name": "Citadel Floor"
    },
    {
      "Id": 2602,
      "Name": "Earth [Alternate]",
      "Description": "Indestructible"
    },
    {
      "Id": 2603,
      "Name": "Earth [Alternate]",
      "Description": "Indestructible"
    },
    {
      "Id": 2604,
      "Name": "Earth [Alternate]",
      "Description": "Indestructible"
    },
    {
      "Id": 2605,
      "Name": "Earth [Alternate]",
      "Description": "Indestructible"
    },
    {
      "Id": 2606,
      "Name": "Earth [Alternate]",
      "Description": "Indestructible"
    },
    {
      "Id": 2607,
      "Name": "Earth [Alternate]",
      "Description": "Indestructible"
    },
    {
      "Id": 2608,
      "Name": "??",
      "Description": "??"
    },
    {
      "Id": 2609,
      "Name": "Plaster"
    },
    {
      "Id": 2610,
      "Name": "Plaster [White]"
    },
    {
      "Id": 2611,
      "Name": "Plaster [Black]"
    },
    {
      "Id": 2612,
      "Name": "Plaster [Purple]"
    },
    {
      "Id": 2613,
      "Name": "Plaster [Pink]"
    },
    {
      "Id": 2614,
      "Name": "Plaster [Red]"
    },
    {
      "Id": 2615,
      "Name": "Plaster [Green]"
    },
    {
      "Id": 2616,
      "Name": "Plaster [Yellow]"
    },
    {
      "Id": 2617,
      "Name": "Plaster [Blue]"
    },
    {
      "Id": 2618,
      "Name": "Floorboard [White]"
    },
    {
      "Id": 2619,
      "Name": "Floorboard [Black]"
    },
    {
      "Id": 2620,
      "Name": "Floorboard [Purple]"
    },
    {
      "Id": 2621,
      "Name": "Floorboard [Pink]"
    },
    {
      "Id": 2622,
      "Name": "Floorboard [Red]"
    },
    {
      "Id": 2623,
      "Name": "Floorboard [Green]"
    },
    {
      "Id": 2624,
      "Name": "Floorboard [Yellow]"
    },
    {
      "Id": 2625,
      "Name": "Floorboard [Blue]"
    },
    {
      "Id": 2626,
      "Name": "Padded Floor [White]"
    },
    {
      "Id": 2627,
      "Name": "Padded Floor [Black]"
    },
    {
      "Id": 2628,
      "Name": "Padded Floor [Purple]"
    },
    {
      "Id": 2629,
      "Name": "Padded Floor [Pink]"
    },
    {
      "Id": 2630,
      "Name": "Padded Floor [Red]"
    },
    {
      "Id": 2631,
      "Name": "Padded Floor [Green]"
    },
    {
      "Id": 2632,
      "Name": "Padded Floor [Yellow]"
    },
    {
      "Id": 2633,
      "Name": "Padded Floor [Blue]"
    },
    {
      "Id": 2634,
      "Name": "Stony Soil [Alternate 1]"
    },
    {
      "Id": 2635,
      "Name": "Stony Soil [Alternate 2]"
    },
    {
      "Id": 2636,
      "Name": "Iron Block"
    },
    {
      "Id": 2637,
      "Name": "Concrete Block"
    },
    {
      "Id": 2638,
      "Name": "Sun Sigil Block"
    },
    {
      "Id": 2639,
      "Name": "Star Sigil Block"
    },
    {
      "Id": 2640,
      "Name": "Moon Sigil Block"
    },
    {
      "Id": 2641,
      "Name": "Water Sigil Block"
    },
    {
      "Id": 2642,
      "Name": "Soul Sigil Block"
    },
    {
      "Id": 2643,
      "Name": "Sandstone Brick"
    },
    {
      "Id": 2644,
      "Name": "Withered Leaves"
    },
    {
      "Id": 2645,
      "Name": "??"
    },
    {
      "Id": 2646,
      "Name": "??",
      "Description": "Indestructible"
    },
    {
      "Id": 2647,
      "Name": "??",
      "Description": "Indestructible"
    },
    {
      "Id": 2648,
      "Name": "??",
      "Description": "Indestructible"
    },
    {
      "Id": 2649,
      "Name": "??",
      "Description": "Indestructible"
    },
    {
      "Id": 2650,
      "Name": "??",
      "Description": "Indestructible"
    },
    {
      "Id": 2651,
      "Name": "??",
      "Description": "Indestructible"
    },
    {
      "Id": 2652,
      "Name": "??",
      "Description": "Indestructible"
    },
    {
      "Id": 2653,
      "Name": "??",
      "Description": "Indestructible"
    },
    {
      "Id": 2654,
      "Name": "Sanguine Sandstone"
    },
    {
      "Id": 2655,
      "Name": "Sanguine Cinders"
    },
    {
      "Id": 2656,
      "Name": "Sanguine Sand"
    },
    {
      "Id": 2657,
      "Name": "Sanguine Sandy Sandstone"
    },
    {
      "Id": 2658,
      "Name": "Scales"
    },
    {
      "Id": 2659,
      "Name": "??",
      "Description": "Indestructible"
    },
    {
      "Id": 2660,
      "Name": "Silver Brick"
    },
    {
      "Id": 2661,
      "Name": "Sooty Silver Brick"
    },
    {
      "Id": 2662,
      "Name": "Seeded Spoiled Soil",
      "Description": "Drops Grass Seed x3"
    },
    {
      "Id": 2663,
      "Name": "Seeded Spoiled Soil",
      "Description": "Drops Tomato Seed x3"
    },
    {
      "Id": 2664,
      "Name": "Seeded Spoiled Soil",
      "Description": "Drops Sugar Cane Seedling x3"
    },
    {
      "Id": 2665,
      "Name": "Seeded Spoiled Soil",
      "Description": "Drops Pumpkin Seed x1"
    },
    {
      "Id": 2666,
      "Name": "Seeded Spoiled Soil",
      "Description": "Drops Pumpkin Seed x3"
    },
    {
      "Id": 2667,
      "Name": "??",
      "Description": "Indestructible"
    },
    {
      "Id": 2668,
      "Name": "??",
      "Description": "Indestructible"
    },
    {
      "Id": 2669,
      "Name": "??",
      "Description": "Indestructible"
    },
    {
      "Id": 2670,
      "Name": "??",
      "Description": "Indestructible"
    },
    {
      "Id": 2671,
      "Name": "??",
      "Description": "Indestructible"
    },
    {
      "Id": 2672,
      "Name": "Silver Tile"
    },
    {
      "Id": 2673,
      "Name": "Dark Dolomite [Alternate]"
    },
    {
      "Id": 2674,
      "Name": "Light Dolomite"
    },
    {
      "Id": 2675,
      "Name": "Clodstone"
    },
    {
      "Id": 2676,
      "Name": "Earth [Alternate]",
      "Description": "Indestructible"
    },
    {
      "Id": 2677,
      "Name": "Earth [Alternate]",
      "Description": "Indestructible"
    },
    {
      "Id": 2678,
      "Name": "Masonry Wall"
    },
    {
      "Id": 2679,
      "Name": "Patterned Vault Wall"
    },
    {
      "Id": 2680,
      "Name": "Patterned Vault Wall"
    },
    {
      "Id": 2681,
      "Name": "Vault Tile"
    },
    {
      "Id": 2682,
      "Name": "Vault Wall"
    },
    {
      "Id": 2683,
      "Name": "Viny Vault Wall"
    },
    {
      "Id": 2684,
      "Name": "Cracked Vault Wall"
    },
    {
      "Id": 2685,
      "Name": "??",
      "Description": "Indestructible"
    },
    {
      "Id": 2686,
      "Name": "Iron Block [White]"
    },
    {
      "Id": 2687,
      "Name": "Iron Block [Black]"
    },
    {
      "Id": 2688,
      "Name": "Iron Block [Purple]"
    },
    {
      "Id": 2689,
      "Name": "Iron Block [Pink]"
    },
    {
      "Id": 2690,
      "Name": "Iron Block [Red]"
    },
    {
      "Id": 2691,
      "Name": "Iron Block [Green]"
    },
    {
      "Id": 2692,
      "Name": "Iron Block [Yellow]"
    },
    {
      "Id": 2693,
      "Name": "Iron Block [Blue]"
    },
    {
      "Id": 2694,
      "Name": "Sandstone Brick [White]"
    },
    {
      "Id": 2695,
      "Name": "Sandstone Brick [Black]"
    },
    {
      "Id": 2696,
      "Name": "Sandstone Brick [Purple]"
    },
    {
      "Id": 2697,
      "Name": "Sandstone Brick [Pink]"
    },
    {
      "Id": 2698,
      "Name": "Sandstone Brick [Red]"
    },
    {
      "Id": 2699,
      "Name": "Sandstone Brick [Green]"
    },
    {
      "Id": 2700,
      "Name": "Sandstone Brick [Yellow]"
    },
    {
      "Id": 2701,
      "Name": "Sandstone Brick [Blue]"
    },
    {
      "Id": 2702,
      "Name": "Castle Tile [White]"
    },
    {
      "Id": 2703,
      "Name": "Castle Tile [Black]"
    },
    {
      "Id": 2704,
      "Name": "Castle Tile [Purple]"
    },
    {
      "Id": 2705,
      "Name": "Castle Tile [Pink]"
    },
    {
      "Id": 2706,
      "Name": "Castle Tile [Red]"
    },
    {
      "Id": 2707,
      "Name": "Castle Tile [Green]"
    },
    {
      "Id": 2708,
      "Name": "Castle Tile [Yellow]"
    },
    {
      "Id": 2709,
      "Name": "Castle Tile [Blue]"
    },
    {
      "Id": 2710,
      "Name": "Carved Castle Tile [White]"
    },
    {
      "Id": 2711,
      "Name": "Carved Castle Tile [Black]"
    },
    {
      "Id": 2712,
      "Name": "Carved Castle Tile [Purple]"
    },
    {
      "Id": 2713,
      "Name": "Carved Castle Tile [Pink]"
    },
    {
      "Id": 2714,
      "Name": "Carved Castle Tile [Red]"
    },
    {
      "Id": 2715,
      "Name": "Carved Castle Tile [Green]"
    },
    {
      "Id": 2716,
      "Name": "Carved Castle Tile [Yellow]"
    },
    {
      "Id": 2717,
      "Name": "Carved Castle Tile [Blue]"
    },
    {
      "Id": 2718,
      "Name": "<<Blue>>",
      "Description": "No collision"
    },
    {
      "Id": 2719,
      "Name": "<<Green>>",
      "Description": "No collision"
    },
    {
      "Id": 2720,
      "Name": "<<Purple>>",
      "Description": "No collision"
    },
    {
      "Id": 2721,
      "Name": "<<Black>>",
      "Description": "No collision"
    },
    {
      "Id": 2722,
      "Name": "<<Yellow>>",
      "Description": "No collision"
    },
    {
      "Id": 2723,
      "Name": "<<Orange>>",
      "Description": "No collision"
    },
    {
      "Id": 2724,
      "Name": "<<Blue>>",
      "Description": "No collision"
    },
    {
      "Id": 2725,
      "Name": "<<Blue>>",
      "Description": "No collision"
    },
    {
      "Id": 2726,
      "Name": "Bronze Temple Tile"
    },
    {
      "Id": 2727,
      "Name": "Blue Temple Tile"
    },
    {
      "Id": 2728,
      "Name": "??",
      "Description": "Drops Strawberry Seed x2"
    },
    {
      "Id": 2729,
      "Name": "??",
      "Description": "Drops Aubergette Seed x2"
    },
    {
      "Id": 2730,
      "Name": "??",
      "Description": "Drops Sweetcorn Kernel x2"
    },
    {
      "Id": 2731,
      "Name": "??",
      "Description": "Drops Coffee Bean x2"
    },
    {
      "Id": 2732,
      "Name": "??",
      "Description": "Drops Leek Seed x2"
    },
    {
      "Id": 2733,
      "Name": "??",
      "Description": "Drops Melon Seed x2"
    },
    {
      "Id": 2734,
      "Name": "Gravel Block"
    },
    {
      "Id": 2735,
      "Name": "Scaled Wall Block"
    },
    {
      "Id": 2736,
      "Name": "Slatted Wall Block"
    },
    {
      "Id": 2737,
      "Name": "Woven Straw Block"
    },
    {
      "Id": 2738,
      "Name": "Woven Straw Block [Alternate 1]"
    },
    {
      "Id": 2739,
      "Name": "Woven Straw Block [Alternate 2]"
    },
    {
      "Id": 2740,
      "Name": "Woven Straw Block [Alternate 3]"
    },
    {
      "Id": 2741,
      "Name": "Woven Straw Block [Alternate 4]"
    },
    {
      "Id": 2742,
      "Name": "Carved Castle Tile [White]"
    },
    {
      "Id": 2743,
      "Name": "Carved Castle Tile [Black]"
    },
    {
      "Id": 2744,
      "Name": "Carved Castle Tile [Purple]"
    },
    {
      "Id": 2745,
      "Name": "Carved Castle Tile [Pink]"
    },
    {
      "Id": 2746,
      "Name": "Carved Castle Tile [Red]"
    },
    {
      "Id": 2747,
      "Name": "Carved Castle Tile [Green]"
    },
    {
      "Id": 2748,
      "Name": "Carved Castle Tile [Yellow]"
    },
    {
      "Id": 2749,
      "Name": "Carved Castle Tile [Blue]"
    },
    {
      "Id": 2750,
      "Name": "Polka-Dot Block"
    },
    {
      "Id": 2751,
      "Name": "Polka-Dot Block [White]"
    },
    {
      "Id": 2752,
      "Name": "Polka-Dot Block [Black]"
    },
    {
      "Id": 2753,
      "Name": "Polka-Dot Block [Purple]"
    },
    {
      "Id": 2754,
      "Name": "Polka-Dot Block [Pink]"
    },
    {
      "Id": 2755,
      "Name": "Polka-Dot Block [Red]"
    },
    {
      "Id": 2756,
      "Name": "Polka-Dot Block [Green]"
    },
    {
      "Id": 2757,
      "Name": "Polka-Dot Block [Yellow]"
    },
    {
      "Id": 2758,
      "Name": "Polka-Dot Block [Blue]"
    },
    {
      "Id": 2759,
      "Name": "Faux Floral Floor Block"
    },
    {
      "Id": 2760,
      "Name": "Palm-Patterned Block"
    },
    {
      "Id": 2761,
      "Name": "Fruity Fiend Block"
    },
    {
      "Id": 2762,
      "Name": "Chequered Block"
    },
    {
      "Id": 2763,
      "Name": "Sunset-Styled Block"
    },
    {
      "Id": 2764,
      "Name": "Seaweed-Styled Block"
    },
    {
      "Id": 2765,
      "Name": "Stylish Stripy Block"
    },
    {
      "Id": 2766,
      "Name": "Seaside Scene Block"
    },
    {
      "Id": 2767,
      "Name": "Abstract Floral Floor Block"
    },
    {
      "Id": 2768,
      "Name": "Herringbone Floorboard Block"
    },
    {
      "Id": 2769,
      "Name": "Night Sky Wall Block"
    },
    {
      "Id": 2770,
      "Name": "Granite Floor Block"
    },
    {
      "Id": 2771,
      "Name": "Stucco Wall Block"
    },
    {
      "Id": 2772,
      "Name": "Stucco Wall Block [White]"
    },
    {
      "Id": 2773,
      "Name": "Stucco Wall Block [Black]"
    },
    {
      "Id": 2774,
      "Name": "Stucco Wall Block [Purple]"
    },
    {
      "Id": 2775,
      "Name": "Stucco Wall Block [Pink]"
    },
    {
      "Id": 2776,
      "Name": "Stucco Wall Block [Red]"
    },
    {
      "Id": 2777,
      "Name": "Stucco Wall Block [Green]"
    },
    {
      "Id": 2778,
      "Name": "Stucco Wall Block [Yellow]"
    },
    {
      "Id": 2779,
      "Name": "Stucco Wall Block [Blue]"
    },
    {
      "Id": 2780,
      "Name": "Palm-Patterned Block [White]"
    },
    {
      "Id": 2781,
      "Name": "Palm-Patterned Block [Black]"
    },
    {
      "Id": 2782,
      "Name": "Palm-Patterned Block [Purple]"
    },
    {
      "Id": 2783,
      "Name": "Palm-Patterned Block [Pink]"
    },
    {
      "Id": 2784,
      "Name": "Palm-Patterned Block [Red]"
    },
    {
      "Id": 2785,
      "Name": "Palm-Patterned Block [Green]"
    },
    {
      "Id": 2786,
      "Name": "Palm-Patterned Block [Yellow]"
    },
    {
      "Id": 2787,
      "Name": "Palm-Patterned Block [Blue]"
    },
    {
      "Id": 2788,
      "Name": "Chequered Block [White]"
    },
    {
      "Id": 2789,
      "Name": "Chequered Block [Black]"
    },
    {
      "Id": 2790,
      "Name": "Chequered Block [Purple]"
    },
    {
      "Id": 2791,
      "Name": "Chequered Block [Pink]"
    },
    {
      "Id": 2792,
      "Name": "Chequered Block [Red]"
    },
    {
      "Id": 2793,
      "Name": "Chequered Block [Green]"
    },
    {
      "Id": 2794,
      "Name": "Chequered Block [Yellow]"
    },
    {
      "Id": 2795,
      "Name": "Chequered Block [Blue]"
    },
    {
      "Id": 2796,
      "Name": "Stylish Stripy Block [White]"
    },
    {
      "Id": 2797,
      "Name": "Stylish Stripy Block [Black]"
    },
    {
      "Id": 2798,
      "Name": "Stylish Stripy Block [Purple]"
    },
    {
      "Id": 2799,
      "Name": "Stylish Stripy Block [Pink]"
    },
    {
      "Id": 2800,
      "Name": "Stylish Stripy Block [Red]"
    },
    {
      "Id": 2801,
      "Name": "Stylish Stripy Block [Green]"
    },
    {
      "Id": 2802,
      "Name": "Stylish Stripy Block [Yellow]"
    },
    {
      "Id": 2803,
      "Name": "Stylish Stripy Block [Blue]"
    },
    {
      "Id": 2804,
      "Name": "Herringbone Floorboard Block [White]"
    },
    {
      "Id": 2805,
      "Name": "Herringbone Floorboard Block [Black]"
    },
    {
      "Id": 2806,
      "Name": "Herringbone Floorboard Block [Purple]"
    },
    {
      "Id": 2807,
      "Name": "Herringbone Floorboard Block [Pink]"
    },
    {
      "Id": 2808,
      "Name": "Herringbone Floorboard Block [Red]"
    },
    {
      "Id": 2809,
      "Name": "Herringbone Floorboard Block [Green]"
    },
    {
      "Id": 2810,
      "Name": "Herringbone Floorboard Block [Yellow]"
    },
    {
      "Id": 2811,
      "Name": "Herringbone Floorboard Block [Blue]"
    },
    {
      "Id": 2812,
      "Name": "Night Sky Wall Block [White]"
    },
    {
      "Id": 2813,
      "Name": "Night Sky Wall Block [Black]"
    },
    {
      "Id": 2814,
      "Name": "Night Sky Wall Block [Purple]"
    },
    {
      "Id": 2815,
      "Name": "Night Sky Wall Block [Pink]"
    },
    {
      "Id": 2816,
      "Name": "Night Sky Wall Block [Red]"
    },
    {
      "Id": 2817,
      "Name": "Night Sky Wall Block [Green]"
    },
    {
      "Id": 2818,
      "Name": "Night Sky Wall Block [Yellow]"
    },
    {
      "Id": 2819,
      "Name": "Night Sky Wall Block [Blue]"
    },
    {
      "Id": 2820,
      "Name": "Modern Masonry Block"
    },
    {
      "Id": 2821,
      "Name": "Modern Masonry Block [White]"
    },
    {
      "Id": 2822,
      "Name": "Modern Masonry Block [Black]"
    },
    {
      "Id": 2823,
      "Name": "Modern Masonry Block [Purple]"
    },
    {
      "Id": 2824,
      "Name": "Modern Masonry Block [Pink]"
    },
    {
      "Id": 2825,
      "Name": "Modern Masonry Block [Red]"
    },
    {
      "Id": 2826,
      "Name": "Modern Masonry Block [Green]"
    },
    {
      "Id": 2827,
      "Name": "Modern Masonry Block [Yellow]"
    },
    {
      "Id": 2828,
      "Name": "Modern Masonry Block [Blue]"
    },
    {
      "Id": 2829,
      "Name": "Chintzy Block"
    },
    {
      "Id": 2830,
      "Name": "Chintzy Block [White]"
    },
    {
      "Id": 2831,
      "Name": "Chintzy Block [Black]"
    },
    {
      "Id": 2832,
      "Name": "Chintzy Block [Purple]"
    },
    {
      "Id": 2833,
      "Name": "Chintzy Block [Pink]"
    },
    {
      "Id": 2834,
      "Name": "Chintzy Block [Red]"
    },
    {
      "Id": 2835,
      "Name": "Chintzy Block [Green]"
    },
    {
      "Id": 2836,
      "Name": "Chintzy Block [Yellow]"
    },
    {
      "Id": 2837,
      "Name": "Chintzy Block [Blue]"
    },
    {
      "Id": 2838,
      "Name": "Gingham Carpet"
    },
    {
      "Id": 2839,
      "Name": "Gingham Carpet [White]"
    },
    {
      "Id": 2840,
      "Name": "Gingham Carpet [Black]"
    },
    {
      "Id": 2841,
      "Name": "Gingham Carpet [Purple]"
    },
    {
      "Id": 2842,
      "Name": "Gingham Carpet [Pink]"
    },
    {
      "Id": 2843,
      "Name": "Gingham Carpet [Red]"
    },
    {
      "Id": 2844,
      "Name": "Gingham Carpet [Green]"
    },
    {
      "Id": 2845,
      "Name": "Gingham Carpet [Yellow]"
    },
    {
      "Id": 2846,
      "Name": "Gingham Carpet [Blue]"
    },
    {
      "Id": 2847,
      "Name": "Stripy Wall"
    },
    {
      "Id": 2848,
      "Name": "Stripy Wall [White]"
    },
    {
      "Id": 2849,
      "Name": "Stripy Wall [Black]"
    },
    {
      "Id": 2850,
      "Name": "Stripy Wall [Purple]"
    },
    {
      "Id": 2851,
      "Name": "Stripy Wall [Pink]"
    },
    {
      "Id": 2852,
      "Name": "Stripy Wall [Red]"
    },
    {
      "Id": 2853,
      "Name": "Stripy Wall [Green]"
    },
    {
      "Id": 2854,
      "Name": "Stripy Wall [Yellow]"
    },
    {
      "Id": 2855,
      "Name": "Stripy Wall [Blue]"
    },
    {
      "Id": 2856,
      "Name": "Mottled Wall"
    },
    {
      "Id": 2857,
      "Name": "Mottled Wall [White]"
    },
    {
      "Id": 2858,
      "Name": "Mottled Wall [Black]"
    },
    {
      "Id": 2859,
      "Name": "Mottled Wall [Purple]"
    },
    {
      "Id": 2860,
      "Name": "Mottled Wall [Pink]"
    },
    {
      "Id": 2861,
      "Name": "Mottled Wall [Red]"
    },
    {
      "Id": 2862,
      "Name": "Mottled Wall [Green]"
    },
    {
      "Id": 2863,
      "Name": "Mottled Wall [Yellow]"
    },
    {
      "Id": 2864,
      "Name": "Mottled Wall [Blue]"
    },
    {
      "Id": 2865,
      "Name": "Slimy Wall"
    },
    {
      "Id": 2866,
      "Name": "Diamond Design Block"
    },
    {
      "Id": 2867,
      "Name": "Old-Skool Wall Block"
    },
    {
      "Id": 2868,
      "Name": "Art Deco Block"
    },
    {
      "Id": 2869,
      "Name": "Jungle Wall"
    },
    {
      "Id": 2870,
      "Name": "Vintage Wall"
    },
    {
      "Id": 2871,
      "Name": "Damask Design Block"
    },
    {
      "Id": 2872,
      "Name": "Damask Design Block [White]"
    },
    {
      "Id": 2873,
      "Name": "Damask Design Block [Black]"
    },
    {
      "Id": 2874,
      "Name": "Damask Design Block [Purple]"
    },
    {
      "Id": 2875,
      "Name": "Damask Design Block [Pink]"
    },
    {
      "Id": 2876,
      "Name": "Damask Design Block [Red]"
    },
    {
      "Id": 2877,
      "Name": "Damask Design Block [Green]"
    },
    {
      "Id": 2878,
      "Name": "Damask Design Block [Yellow]"
    },
    {
      "Id": 2879,
      "Name": "Damask Design Block [Blue]"
    },
    {
      "Id": 2880,
      "Name": "Refined Design Block"
    },
    {
      "Id": 2881,
      "Name": "Classy Cross Block"
    },
    {
      "Id": 2882,
      "Name": "Sunset-Styled Block [White]"
    },
    {
      "Id": 2883,
      "Name": "Sunset-Styled Block [Black]"
    },
    {
      "Id": 2884,
      "Name": "Sunset-Styled Block [Purple]"
    },
    {
      "Id": 2885,
      "Name": "Sunset-Styled Block [Pink]"
    },
    {
      "Id": 2886,
      "Name": "Sunset-Styled Block [Red]"
    },
    {
      "Id": 2887,
      "Name": "Sunset-Styled Block [Green]"
    },
    {
      "Id": 2888,
      "Name": "Sunset-Styled Block [Yellow]"
    },
    {
      "Id": 2889,
      "Name": "Sunset-Styled Block [Blue]"
    },
    {
      "Id": 2890,
      "Name": "Seaweed-Styled Block [White]"
    },
    {
      "Id": 2891,
      "Name": "Seaweed-Styled Block [Black]"
    },
    {
      "Id": 2892,
      "Name": "Seaweed-Styled Block [Purple]"
    },
    {
      "Id": 2893,
      "Name": "Seaweed-Styled Block [Pink]"
    },
    {
      "Id": 2894,
      "Name": "Seaweed-Styled Block [Red]"
    },
    {
      "Id": 2895,
      "Name": "Seaweed-Styled Block [Green]"
    },
    {
      "Id": 2896,
      "Name": "Seaweed-Styled Block [Yellow]"
    },
    {
      "Id": 2897,
      "Name": "Seaweed-Styled Block [Blue]"
    },
    {
      "Id": 2898,
      "Name": "Vintage Wall [White]"
    },
    {
      "Id": 2899,
      "Name": "Vintage Wall [Black]"
    },
    {
      "Id": 2900,
      "Name": "Vintage Wall [Purple]"
    },
    {
      "Id": 2901,
      "Name": "Vintage Wall [Pink]"
    },
    {
      "Id": 2902,
      "Name": "Vintage Wall [Red]"
    },
    {
      "Id": 2903,
      "Name": "Vintage Wall [Green]"
    },
    {
      "Id": 2904,
      "Name": "Vintage Wall [Yellow]"
    },
    {
      "Id": 2905,
      "Name": "Vintage Wall [Blue]"
    },
    {
      "Id": 2906,
      "Name": "Earth [Alternate]",
      "Description": "Indestructible"
    },
    {
      "Id": 2907,
      "Name": "Earth [Alternate]",
      "Description": "Indestructible"
    },
    {
      "Id": 2908,
      "Name": "Earth [Alternate]",
      "Description": "Indestructible"
    },
    {
      "Id": 2909,
      "Name": "Earth [Alternate]",
      "Description": "Indestructible"
    },
    {
      "Id": 2910,
      "Name": "Earth [Alternate]",
      "Description": "Indestructible"
    },
    {
      "Id": 2911,
      "Name": "Earth [Alternate]",
      "Description": "Indestructible"
    },
    {
      "Id": 2912,
      "Name": "Earth [Alternate]",
      "Description": "Indestructible"
    },
    {
      "Id": 2913,
      "Name": "Earth [Alternate]",
      "Description": "Indestructible"
    },
    {
      "Id": 2914,
      "Name": "Earth [Alternate]",
      "Description": "Indestructible"
    },
    {
      "Id": 2915,
      "Name": "Earth [Alternate]",
      "Description": "Indestructible"
    },
    {
      "Id": 2916,
      "Name": "Earth [Alternate]",
      "Description": "Indestructible"
    },
    {
      "Id": 2917,
      "Name": "Earth [Alternate]",
      "Description": "Indestructible"
    },
    {
      "Id": 2918,
      "Name": "Earth [Alternate]",
      "Description": "Indestructible"
    },
    {
      "Id": 2919,
      "Name": "Earth [Alternate]",
      "Description": "Indestructible"
    },
    {
      "Id": 2920,
      "Name": "Earth [Alternate]",
      "Description": "Indestructible"
    },
    {
      "Id": 2921,
      "Name": "Earth [Alternate]",
      "Description": "Indestructible"
    },
    {
      "Id": 2922,
      "Name": "Earth [Alternate]",
      "Description": "Indestructible"
    },
    {
      "Id": 2923,
      "Name": "Earth [Alternate]",
      "Description": "Indestructible"
    },
    {
      "Id": 2924,
      "Name": "Earth [Alternate]",
      "Description": "Indestructible"
    },
    {
      "Id": 2925,
      "Name": "Earth [Alternate]",
      "Description": "Indestructible"
    },
    {
      "Id": 2926,
      "Name": "Earth [Alternate]",
      "Description": "Indestructible"
    },
    {
      "Id": 2927,
      "Name": "Earth [Alternate]",
      "Description": "Indestructible"
    },
    {
      "Id": 2928,
      "Name": "Earth [Alternate]",
      "Description": "Indestructible"
    },
    {
      "Id": 2929,
      "Name": "Earth [Alternate]",
      "Description": "Indestructible"
    },
    {
      "Id": 2930,
      "Name": "Earth [Alternate]",
      "Description": "Indestructible"
    },
    {
      "Id": 2931,
      "Name": "Earth [Alternate]",
      "Description": "Indestructible"
    },
    {
      "Id": 2932,
      "Name": "Earth [Alternate]",
      "Description": "Indestructible"
    },
    {
      "Id": 2933,
      "Name": "Earth [Alternate]",
      "Description": "Indestructible"
    },
    {
      "Id": 2934,
      "Name": "Earth [Alternate]",
      "Description": "Indestructible"
    },
    {
      "Id": 2935,
      "Name": "Earth [Alternate]",
      "Description": "Indestructible"
    },
    {
      "Id": 2936,
      "Name": "Earth [Alternate]",
      "Description": "Indestructible"
    },
    {
      "Id": 2937,
      "Name": "Earth [Alternate]",
      "Description": "Indestructible"
    },
    {
      "Id": 2938,
      "Name": "Earth [Alternate]",
      "Description": "Indestructible"
    },
    {
      "Id": 2939,
      "Name": "Earth [Alternate]",
      "Description": "Indestructible"
    },
    {
      "Id": 2940,
      "Name": "Earth [Alternate]",
      "Description": "Indestructible"
    },
    {
      "Id": 2941,
      "Name": "Earth [Alternate]",
      "Description": "Indestructible"
    },
    {
      "Id": 2942,
      "Name": "Earth [Alternate]",
      "Description": "Indestructible"
    },
    {
      "Id": 2943,
      "Name": "Earth [Alternate]",
      "Description": "Indestructible"
    },
    {
      "Id": 2944,
      "Name": "Earth [Alternate]",
      "Description": "Indestructible"
    },
    {
      "Id": 2945,
      "Name": "Earth [Alternate]",
      "Description": "Indestructible"
    },
    {
      "Id": 2946,
      "Name": "Earth [Alternate]",
      "Description": "Indestructible"
    },
    {
      "Id": 2947,
      "Name": "Earth [Alternate]",
      "Description": "Indestructible"
    },
    {
      "Id": 2948,
      "Name": "Earth [Alternate]",
      "Description": "Indestructible"
    },
    {
      "Id": 2949,
      "Name": "Earth [Alternate]",
      "Description": "Indestructible"
    },
    {
      "Id": 2950,
      "Name": "Earth [Alternate]",
      "Description": "Indestructible"
    },
    {
      "Id": 2951,
      "Name": "Earth [Alternate]",
      "Description": "Indestructible"
    },
    {
      "Id": 2952,
      "Name": "Earth [Alternate]",
      "Description": "Indestructible"
    },
    {
      "Id": 2953,
      "Name": "Earth [Alternate]",
      "Description": "Indestructible"
    },
    {
      "Id": 2954,
      "Name": "Earth [Alternate]",
      "Description": "Indestructible"
    },
    {
      "Id": 2955,
      "Name": "Earth [Alternate]",
      "Description": "Indestructible"
    },
    {
      "Id": 2956,
      "Name": "Earth [Alternate]",
      "Description": "Indestructible"
    },
    {
      "Id": 2957,
      "Name": "Earth [Alternate]",
      "Description": "Indestructible"
    },
    {
      "Id": 2958,
      "Name": "Earth [Alternate]",
      "Description": "Indestructible"
    },
    {
      "Id": 2959,
      "Name": "Earth [Alternate]",
      "Description": "Indestructible"
    },
    {
      "Id": 2960,
      "Name": "Earth [Alternate]",
      "Description": "Indestructible"
    },
    {
      "Id": 2961,
      "Name": "Earth [Alternate]",
      "Description": "Indestructible"
    },
    {
      "Id": 2962,
      "Name": "Earth [Alternate]",
      "Description": "Indestructible"
    },
    {
      "Id": 2963,
      "Name": "Earth [Alternate]",
      "Description": "Indestructible"
    },
    {
      "Id": 2964,
      "Name": "Earth [Alternate]",
      "Description": "Indestructible"
    },
    {
      "Id": 2965,
      "Name": "Earth [Alternate]",
      "Description": "Indestructible"
    },
    {
      "Id": 2966,
      "Name": "Earth [Alternate]",
      "Description": "Indestructible"
    },
    {
      "Id": 2967,
      "Name": "Earth [Alternate]",
      "Description": "Indestructible"
    },
    {
      "Id": 2968,
      "Name": "Earth [Alternate]",
      "Description": "Indestructible"
    },
    {
      "Id": 2969,
      "Name": "Earth [Alternate]",
      "Description": "Indestructible"
    },
    {
      "Id": 2970,
      "Name": "Earth [Alternate]",
      "Description": "Indestructible"
    },
    {
      "Id": 2971,
      "Name": "Earth [Alternate]",
      "Description": "Indestructible"
    },
    {
      "Id": 2972,
      "Name": "Earth [Alternate]",
      "Description": "Indestructible"
    },
    {
      "Id": 2973,
      "Name": "Earth [Alternate]",
      "Description": "Indestructible"
    },
    {
      "Id": 2974,
      "Name": "Earth [Alternate]",
      "Description": "Indestructible"
    },
    {
      "Id": 2975,
      "Name": "Earth [Alternate]",
      "Description": "Indestructible"
    },
    {
      "Id": 2976,
      "Name": "Earth [Alternate]",
      "Description": "Indestructible"
    },
    {
      "Id": 2977,
      "Name": "Earth [Alternate]",
      "Description": "Indestructible"
    },
    {
      "Id": 2978,
      "Name": "Earth [Alternate]",
      "Description": "Indestructible"
    },
    {
      "Id": 2979,
      "Name": "Earth [Alternate]",
      "Description": "Indestructible"
    },
    {
      "Id": 2980,
      "Name": "Earth [Alternate]",
      "Description": "Indestructible"
    },
    {
      "Id": 2981,
      "Name": "Earth [Alternate]",
      "Description": "Indestructible"
    },
    {
      "Id": 2982,
      "Name": "Earth [Alternate]",
      "Description": "Indestructible"
    },
    {
      "Id": 2983,
      "Name": "Earth [Alternate]",
      "Description": "Indestructible"
    },
    {
      "Id": 2984,
      "Name": "Earth [Alternate]",
      "Description": "Indestructible"
    },
    {
      "Id": 2985,
      "Name": "Earth [Alternate]",
      "Description": "Indestructible"
    },
    {
      "Id": 2986,
      "Name": "Earth [Alternate]",
      "Description": "Indestructible"
    },
    {
      "Id": 2987,
      "Name": "Earth [Alternate]",
      "Description": "Indestructible"
    },
    {
      "Id": 2988,
      "Name": "Earth [Alternate]",
      "Description": "Indestructible"
    },
    {
      "Id": 2989,
      "Name": "Earth [Alternate]",
      "Description": "Indestructible"
    },
    {
      "Id": 2990,
      "Name": "Earth [Alternate]",
      "Description": "Indestructible"
    },
    {
      "Id": 2991,
      "Name": "Earth [Alternate]",
      "Description": "Indestructible"
    },
    {
      "Id": 2992,
      "Name": "Earth [Alternate]",
      "Description": "Indestructible"
    },
    {
      "Id": 2993,
      "Name": "Earth [Alternate]",
      "Description": "Indestructible"
    },
    {
      "Id": 2994,
      "Name": "Earth [Alternate]",
      "Description": "Indestructible"
    },
    {
      "Id": 2995,
      "Name": "Earth [Alternate]",
      "Description": "Indestructible"
    },
    {
      "Id": 2996,
      "Name": "Earth [Alternate]",
      "Description": "Indestructible"
    },
    {
      "Id": 2997,
      "Name": "Earth [Alternate]",
      "Description": "Indestructible"
    },
    {
      "Id": 2998,
      "Name": "Earth [Alternate]",
      "Description": "Indestructible"
    },
    {
      "Id": 2999,
      "Name": "Earth [Alternate]",
      "Description": "Indestructible"
    },
    {
      "Id": 3000,
      "Name": "Earth [Alternate]",
      "Description": "Indestructible"
    },
    {
      "Id": 3001,
      "Name": "Earth [Alternate]",
      "Description": "Indestructible"
    },
    {
      "Id": 3002,
      "Name": "Earth [Alternate]",
      "Description": "Indestructible"
    },
    {
      "Id": 3003,
      "Name": "Earth [Alternate]",
      "Description": "Indestructible"
    },
    {
      "Id": 3004,
      "Name": "Earth [Alternate]",
      "Description": "Indestructible"
    },
    {
      "Id": 3005,
      "Name": "Earth [Alternate]",
      "Description": "Indestructible"
    },
    {
      "Id": 3006,
      "Name": "Earth [Alternate]",
      "Description": "Indestructible"
    },
    {
      "Id": 3007,
      "Name": "Earth [Alternate]",
      "Description": "Indestructible"
    },
    {
      "Id": 3008,
      "Name": "Earth [Alternate]",
      "Description": "Indestructible"
    },
    {
      "Id": 3009,
      "Name": "Earth [Alternate]",
      "Description": "Indestructible"
    },
    {
      "Id": 3010,
      "Name": "Earth [Alternate]",
      "Description": "Indestructible"
    },
    {
      "Id": 3011,
      "Name": "Earth [Alternate]",
      "Description": "Indestructible"
    },
    {
      "Id": 3012,
      "Name": "Earth [Alternate]",
      "Description": "Indestructible"
    },
    {
      "Id": 3013,
      "Name": "Earth [Alternate]",
      "Description": "Indestructible"
    },
    {
      "Id": 3014,
      "Name": "Earth [Alternate]",
      "Description": "Indestructible"
    },
    {
      "Id": 3015,
      "Name": "Earth [Alternate]",
      "Description": "Indestructible"
    },
    {
      "Id": 3016,
      "Name": "Earth [Alternate]",
      "Description": "Indestructible"
    },
    {
      "Id": 3017,
      "Name": "Earth [Alternate]",
      "Description": "Indestructible"
    },
    {
      "Id": 3018,
      "Name": "Earth [Alternate]",
      "Description": "Indestructible"
    },
    {
      "Id": 3019,
      "Name": "Earth [Alternate]",
      "Description": "Indestructible"
    },
    {
      "Id": 3020,
      "Name": "Earth [Alternate]",
      "Description": "Indestructible"
    },
    {
      "Id": 3021,
      "Name": "Earth [Alternate]",
      "Description": "Indestructible"
    },
    {
      "Id": 3022,
      "Name": "Earth [Alternate]",
      "Description": "Indestructible"
    },
    {
      "Id": 3023,
      "Name": "Earth [Alternate]",
      "Description": "Indestructible"
    },
    {
      "Id": 3024,
      "Name": "Earth [Alternate]",
      "Description": "Indestructible"
    },
    {
      "Id": 3025,
      "Name": "Earth [Alternate]",
      "Description": "Indestructible"
    },
    {
      "Id": 3026,
      "Name": "Earth [Alternate]",
      "Description": "Indestructible"
    },
    {
      "Id": 3027,
      "Name": "Earth [Alternate]",
      "Description": "Indestructible"
    },
    {
      "Id": 3028,
      "Name": "Earth [Alternate]",
      "Description": "Indestructible"
    },
    {
      "Id": 3029,
      "Name": "Earth [Alternate]",
      "Description": "Indestructible"
    },
    {
      "Id": 3030,
      "Name": "Earth [Alternate]",
      "Description": "Indestructible"
    },
    {
      "Id": 3031,
      "Name": "Earth [Alternate]",
      "Description": "Indestructible"
    },
    {
      "Id": 3032,
      "Name": "Earth [Alternate]",
      "Description": "Indestructible"
    },
    {
      "Id": 3033,
      "Name": "Earth [Alternate]",
      "Description": "Indestructible"
    },
    {
      "Id": 3034,
      "Name": "Earth [Alternate]",
      "Description": "Indestructible"
    },
    {
      "Id": 3035,
      "Name": "Earth [Alternate]",
      "Description": "Indestructible"
    },
    {
      "Id": 3036,
      "Name": "Earth [Alternate]",
      "Description": "Indestructible"
    },
    {
      "Id": 3037,
      "Name": "Earth [Alternate]",
      "Description": "Indestructible"
    },
    {
      "Id": 3038,
      "Name": "Earth [Alternate]",
      "Description": "Indestructible"
    },
    {
      "Id": 3039,
      "Name": "Earth [Alternate]",
      "Description": "Indestructible"
    },
    {
      "Id": 3040,
      "Name": "Earth [Alternate]",
      "Description": "Indestructible"
    },
    {
      "Id": 3041,
      "Name": "Earth [Alternate]",
      "Description": "Indestructible"
    },
    {
      "Id": 3042,
      "Name": "Earth [Alternate]",
      "Description": "Indestructible"
    },
    {
      "Id": 3043,
      "Name": "Earth [Alternate]",
      "Description": "Indestructible"
    },
    {
      "Id": 3044,
      "Name": "Earth [Alternate]",
      "Description": "Indestructible"
    },
    {
      "Id": 3045,
      "Name": "Earth [Alternate]",
      "Description": "Indestructible"
    },
    {
      "Id": 3046,
      "Name": "Earth [Alternate]",
      "Description": "Indestructible"
    },
    {
      "Id": 3047,
      "Name": "Earth [Alternate]",
      "Description": "Indestructible"
    },
    {
      "Id": 3048,
      "Name": "Earth [Alternate]",
      "Description": "Indestructible"
    },
    {
      "Id": 3049,
      "Name": "Earth [Alternate]",
      "Description": "Indestructible"
    },
    {
      "Id": 3050,
      "Name": "Earth [Alternate]",
      "Description": "Indestructible"
    },
    {
      "Id": 3051,
      "Name": "Earth [Alternate]",
      "Description": "Indestructible"
    },
    {
      "Id": 3052,
      "Name": "Earth [Alternate]",
      "Description": "Indestructible"
    },
    {
      "Id": 3053,
      "Name": "Earth [Alternate]",
      "Description": "Indestructible"
    },
    {
      "Id": 3054,
      "Name": "Earth [Alternate]",
      "Description": "Indestructible"
    },
    {
      "Id": 3055,
      "Name": "Earth [Alternate]",
      "Description": "Indestructible"
    },
    {
      "Id": 3056,
      "Name": "Earth [Alternate]",
      "Description": "Indestructible"
    },
    {
      "Id": 3057,
      "Name": "Earth [Alternate]",
      "Description": "Indestructible"
    },
    {
      "Id": 3058,
      "Name": "Earth [Alternate]",
      "Description": "Indestructible"
    },
    {
      "Id": 3059,
      "Name": "Earth [Alternate]",
      "Description": "Indestructible"
    },
    {
      "Id": 3060,
      "Name": "<<Black>>",
      "Description": "Indestructible"
    },
    {
      "Id": 3061,
      "Name": "Earth [Alternate]",
      "Description": "Indestructible"
    },
    {
      "Id": 3062,
      "Name": "Earth [Alternate]",
      "Description": "Indestructible"
    },
    {
      "Id": 3063,
      "Name": "Earth [Alternate]",
      "Description": "Indestructible"
    },
    {
      "Id": 3064,
      "Name": "Earth [Alternate]",
      "Description": "Indestructible"
    },
    {
      "Id": 3065,
      "Name": "Earth [Alternate]",
      "Description": "Indestructible"
    },
    {
      "Id": 3066,
      "Name": "Earth [Alternate]",
      "Description": "Indestructible"
    },
    {
      "Id": 3067,
      "Name": "Earth [Alternate]",
      "Description": "Indestructible"
    },
    {
      "Id": 3068,
      "Name": "Earth [Alternate]",
      "Description": "Indestructible"
    },
    {
      "Id": 3069,
      "Name": "Earth [Alternate]",
      "Description": "Indestructible"
    },
    {
      "Id": 3070,
      "Name": "Earth [Alternate]",
      "Description": "Indestructible"
    },
    {
      "Id": 3071,
      "Name": "Earth [Alternate]",
      "Description": "Indestructible"
    }
  ]
}
